stagingcontext/__init__.py
django_stagingcontext-0.1.0.dist-info/WHEEL
django_stagingcontext-0.1.0.dist-info/METADATA
django_stagingcontext-0.1.0.dist-info/metadata.json
django_stagingcontext-0.1.0.dist-info/DESCRIPTION.rst
django_stagingcontext-0.1.0.dist-info/top_level.txt
django_stagingcontext-0.1.0.dist-info/RECORD
